lunchable/__init__.py
lunchable/__main__.py
lunchable/_cli.py
lunchable/_version.py
lunchable/exceptions.py
lunchable/py.typed
lunchable/_config/__init__.py
lunchable/_config/api_config.py
lunchable/_config/file_config.py
lunchable/_config/logging_config.py
lunchable/models/__init__.py
lunchable/models/_base.py
lunchable/models/_core.py
lunchable/models/_descriptions.py
lunchable/models/_lunchmoney.py
lunchable/models/assets.py
lunchable/models/budgets.py
lunchable/models/categories.py
lunchable/models/crypto.py
lunchable/models/plaid_accounts.py
lunchable/models/recurring_expenses.py
lunchable/models/recurring_items.py
lunchable/models/tags.py
lunchable/models/transactions.py
lunchable/models/user.py
lunchable/plugins/__init__.py
lunchable/plugins/app.py
lunchable-1.4.3.dist-info/METADATA
lunchable-1.4.3.dist-info/WHEEL
lunchable-1.4.3.dist-info/entry_points.txt
lunchable-1.4.3.dist-info/licenses/LICENSE
lunchable-1.4.3.dist-info/RECORD
