Metadata-Version: 2.4
Name: lunchable
Version: 1.4.3
Summary: A simple Python SDK around the Lunch Money Developer API
Project-URL: Changelog, https://github.com/juftin/lunchable/releases
Project-URL: Discussions, https://github.com/juftin/lunchable/discussions
Project-URL: Docker, https://hub.docker.com/r/juftin/lunchable
Project-URL: Documentation, https://github.com/juftin/lunchable#readme
Project-URL: Issues, https://github.com/juftin/lunchable/issues
Project-URL: Source, https://github.com/juftin/lunchable
Author-email: Justin Flannery <juftin@juftin.com>
License-Expression: MIT
License-File: LICENSE
Keywords: api-client,lunchmoney,pydantic,python
Classifier: Development Status :: 5 - Production/Stable
Classifier: License :: OSI Approved :: MIT License
Classifier: Operating System :: OS Independent
Classifier: Programming Language :: Python
Classifier: Programming Language :: Python :: 3.9
Classifier: Programming Language :: Python :: 3.10
Classifier: Programming Language :: Python :: 3.11
Classifier: Programming Language :: Python :: 3.12
Classifier: Programming Language :: Python :: 3.13
Classifier: Programming Language :: Python :: Implementation :: CPython
Classifier: Programming Language :: Python :: Implementation :: PyPy
Requires-Python: <4,>=3.9
Requires-Dist: click-plugins>=1.1.1
Requires-Dist: click>=8.0.1
Requires-Dist: httpx
Requires-Dist: importlib-metadata>=3.6
Requires-Dist: pydantic<3,>=2
Requires-Dist: rich>=10.0.0
Provides-Extra: all
Requires-Dist: lunchable-primelunch; extra == 'all'
Requires-Dist: lunchable-pushlunch; extra == 'all'
Requires-Dist: lunchable-splitlunch; extra == 'all'
Provides-Extra: plugins
Requires-Dist: lunchable-primelunch; extra == 'plugins'
Requires-Dist: lunchable-pushlunch; extra == 'plugins'
Requires-Dist: lunchable-splitlunch; extra == 'plugins'
Provides-Extra: primelunch
Requires-Dist: lunchable-primelunch; extra == 'primelunch'
Provides-Extra: pushlunch
Requires-Dist: lunchable-pushlunch; extra == 'pushlunch'
Provides-Extra: splitlunch
Requires-Dist: lunchable-splitlunch; extra == 'splitlunch'
